arbin_echem_tools/__init__.py
arbin_echem_tools/_version.py
arbin_echem_tools/arbin_echem_tools.py
arbin_echem_tools/cli.py
arbin_echem_tools/parse.py
arbin_echem_tools/parse_gui.py
arbin_echem_tools-0.1.2.dist-info/AUTHORS.rst
arbin_echem_tools-0.1.2.dist-info/LICENSE
arbin_echem_tools-0.1.2.dist-info/METADATA
arbin_echem_tools-0.1.2.dist-info/WHEEL
arbin_echem_tools-0.1.2.dist-info/entry_points.txt
arbin_echem_tools-0.1.2.dist-info/top_level.txt
arbin_echem_tools-0.1.2.dist-info/RECORD
