Metadata-Version: 2.1
Name: arbin-echem-tools
Version: 0.1.2
Summary: Reads raw electrochemical cycling data and generates useful plots and tables for battery scientists.
Home-page: https://github.com/vince-wu/arbin_echem_tools
Author: Vincent Wu
Author-email: vincentwu@ucsb.edu
License: MIT license
Keywords: arbin_echem_tools
Platform: UNKNOWN
Classifier: Development Status :: 2 - Pre-Alpha
Classifier: Intended Audience :: Developers
Classifier: License :: OSI Approved :: MIT License
Classifier: Natural Language :: English
Classifier: Programming Language :: Python :: 3
Classifier: Programming Language :: Python :: 3.5
Classifier: Programming Language :: Python :: 3.6
Classifier: Programming Language :: Python :: 3.7
Classifier: Programming Language :: Python :: 3.8
Requires-Python: >=3.5
Requires-Dist: Click (>=7.0)
